{
  "page": 23,
  "value": [
    {
      "path": "_news/2021-03-20-upstart-ceo-on-applying-ai-to-lending-an-enormous-market-opportunity.md",
      "title": "Upstart CEO on applying AI to lending: 'An enormous market opportunity'",
      "excerpt": "Upstart co-founder and CEO Dave Girouard joined Jim Cramer on \"Mad Money\" to discuss how the online lending platform is using modern technology to solve the biggest problems in the loans business.",
      "sourceUrl": null,
      "webUrl": "https://www.cnbc.com/video/2021/03/19/upstart-ceo-on-an-enormous-market-opportunity-in-tying-ai-to-lending.html",
      "originalUrl": "https://www.cnbc.com/video/2021/03/19/upstart-ceo-on-an-enormous-market-opportunity-in-tying-ai-to-lending.html",
      "featuredContent": null,
      "highlight": null,
      "heat": 77,
      "tags": null,
      "images": [
        {
          "url": "https://image.cnbcfm.com/api/v1/image/106856972-DOTCOM-MM-C-031921-jpg?v=1616194589",
          "width": 400,
          "height": 225,
          "title": null,
          "attribution": null,
          "isCached": true
        }
      ],
      "content": "\r\n",
      "type": "article",
      "ampWebUrl": null,
      "cdnAmpWebUrl": null,
      "publishedDateTime": "2021-03-19T14:56:00-07:00",
      "updatedDateTime": null,
      "provider": {
        "name": "CNBC",
        "domain": "cnbc.com",
        "images": [
          {
            "url": "https://smartableai.github.io/artificial-intelligence/assets/images/organizations/cnbc.com-50x50.jpg",
            "width": 50,
            "height": 50,
            "title": null,
            "attribution": null,
            "isCached": false
          }
        ],
        "publishers": null,
        "authors": null
      },
      "locale": "en-us",
      "categories": [
        "news"
      ],
      "topics": [
        "AI"
      ]
    },
    {
      "path": "_news/2021-03-20-extra-crunch-roundup-ai-eats-fintech-fundraising-visas-no-code-transition-tips-more.md",
      "title": "Extra Crunch roundup: AI eats fintech, fundraising visas, no-code transition tips, more",
      "excerpt": "For this morning’s column, Alex Wilhelm interviewed Dave Girouard, CEO of Upstart, an AI-powered fintech lender that expects to see growth increase 114% this year. A forecast like that suggests ...",
      "sourceUrl": null,
      "webUrl": "https://techcrunch.com/2021/03/19/extra-crunch-roundup-ai-eats-fintech-fundraising-visas-no-code-transition-tips-more/",
      "originalUrl": "https://techcrunch.com/2021/03/19/extra-crunch-roundup-ai-eats-fintech-fundraising-visas-no-code-transition-tips-more/",
      "featuredContent": null,
      "highlight": null,
      "heat": 81,
      "tags": null,
      "images": [
        {
          "url": "https://techcrunch.com/wp-content/uploads/2021/03/GettyImages-908893916.jpg?w=1024",
          "width": 1024,
          "height": 655,
          "title": null,
          "attribution": null,
          "isCached": true
        }
      ],
      "content": "\r\n",
      "type": "article",
      "ampWebUrl": "https://techcrunch.com/2021/03/19/extra-crunch-roundup-ai-eats-fintech-fundraising-visas-no-code-transition-tips-more/amp/",
      "cdnAmpWebUrl": "https://techcrunch-com.cdn.ampproject.org/c/s/techcrunch.com/2021/03/19/extra-crunch-roundup-ai-eats-fintech-fundraising-visas-no-code-transition-tips-more/amp/",
      "publishedDateTime": "2021-03-19T14:38:00-07:00",
      "updatedDateTime": null,
      "provider": {
        "name": "TechCrunch",
        "domain": "techcrunch.com",
        "images": [
          {
            "url": "https://smartableai.github.io/artificial-intelligence/assets/images/organizations/techcrunch.com-50x50.jpg",
            "width": 50,
            "height": 50,
            "title": null,
            "attribution": null,
            "isCached": false
          }
        ],
        "publishers": null,
        "authors": null
      },
      "locale": "en-us",
      "categories": [
        "news"
      ],
      "topics": [
        "AI in Finance",
        "AI"
      ]
    },
    {
      "path": "_news/2021-03-20-does-it-keep-covid-19-out-of-buildings-or-is-it-really-a-facial-recognition-tool.md",
      "title": "Does it keep COVID-19 out of buildings? Or is it really a facial recognition tool?",
      "excerpt": "Tech companies are already preparing automated safety barriers aimed to keep COVID-19 out of buildings. Some, though, may have worrisome aspects. And I'm not just talking about the foot bath.",
      "sourceUrl": null,
      "webUrl": "https://www.zdnet.com/article/does-it-keep-covid-out-of-buildings-or-is-it-really-a-facial-recognition-tool/",
      "originalUrl": "https://www.zdnet.com/article/does-it-keep-covid-out-of-buildings-or-is-it-really-a-facial-recognition-tool/",
      "featuredContent": null,
      "highlight": null,
      "heat": 85,
      "tags": null,
      "images": [
        {
          "url": "https://www.zdnet.com/a/hub/i/2021/03/16/3c173e31-acbb-4aa8-b06a-1c8c98911b8d/screen-shot-2021-03-16-at-3-27-05-pm.png",
          "width": 1672,
          "height": 830,
          "title": null,
          "attribution": null,
          "isCached": true
        }
      ],
      "content": "\r\n",
      "type": "article",
      "ampWebUrl": "https://www.zdnet.com/google-amp/article/does-it-keep-covid-out-of-buildings-or-is-it-really-a-facial-recognition-tool/",
      "cdnAmpWebUrl": "https://www-zdnet-com.cdn.ampproject.org/c/s/www.zdnet.com/google-amp/article/does-it-keep-covid-out-of-buildings-or-is-it-really-a-facial-recognition-tool/",
      "publishedDateTime": "2021-03-19T13:47:00-07:00",
      "updatedDateTime": null,
      "provider": {
        "name": "ZDNet",
        "domain": "zdnet.com",
        "images": [
          {
            "url": "https://smartableai.github.io/artificial-intelligence/assets/images/organizations/zdnet.com-50x50.jpg",
            "width": 50,
            "height": 50,
            "title": null,
            "attribution": null,
            "isCached": false
          }
        ],
        "publishers": null,
        "authors": null
      },
      "locale": "en-us",
      "categories": [
        "news"
      ],
      "topics": [
        "Natural Language Processing",
        "AI",
        "Computer Vision"
      ]
    },
    {
      "path": "_news/2021-03-20-natural-language-processing-market-growing-at-a-cagr-203-key-player-microsoft-google-amazon-web-services-facebook-intel.md",
      "title": "Natural Language Processing Market Growing at a CAGR 20.3% | Key Player Microsoft, Google, Amazon Web Services, Facebook, Intel",
      "excerpt": "and Region – Global Forecast to 2026 The global Natural Language Processing (NLP) Market size to grow from USD 11.6 billion in 2020 to USD 35.1 billion by 2026, at a Compound Annual Growth Rate ...",
      "sourceUrl": null,
      "webUrl": "https://www.benzinga.com/pressreleases/21/03/ab20259676/natural-language-processing-market-growing-at-a-cagr-20-3-key-player-microsoft-google-amazon-web-",
      "originalUrl": "https://www.benzinga.com/pressreleases/21/03/ab20259676/natural-language-processing-market-growing-at-a-cagr-20-3-key-player-microsoft-google-amazon-web-",
      "featuredContent": null,
      "highlight": null,
      "heat": null,
      "tags": null,
      "images": null,
      "content": "\r\n",
      "type": "article",
      "ampWebUrl": "https://amp.benzinga.com/amp/content/20259676",
      "cdnAmpWebUrl": "https://amp-benzinga-com.cdn.ampproject.org/c/s/amp.benzinga.com/amp/content/20259676",
      "publishedDateTime": "2021-03-19T11:51:00-07:00",
      "updatedDateTime": null,
      "provider": {
        "name": "Benzinga.com",
        "domain": "benzinga.com",
        "images": null,
        "publishers": null,
        "authors": null
      },
      "locale": "en-us",
      "categories": [
        "news"
      ],
      "topics": [
        "Natural Language Processing",
        "AI",
        "AWS AI",
        "Microsoft AI"
      ]
    },
    {
      "path": "_news/2021-03-20-uber-under-pressure-over-facial-recognition-checks-for-drivers.md",
      "title": "Uber under pressure over facial recognition checks for drivers",
      "excerpt": "Uber’s use of facial recognition technology for a driver identity system is being challenged in the UK where the App Drivers & Couriers Union (ADCU) and Worker Info Exchange (WIE) have today called for Microsoft to suspend the ride-hailing giant’s use of b2b facial recognition",
      "sourceUrl": null,
      "webUrl": "https://techcrunch.com/2021/03/19/uber-under-pressure-over-facial-recognition-checks-for-drivers/",
      "originalUrl": "https://techcrunch.com/2021/03/19/uber-under-pressure-over-facial-recognition-checks-for-drivers/",
      "featuredContent": null,
      "highlight": null,
      "heat": 109,
      "tags": null,
      "images": [
        {
          "url": "https://techcrunch.com/wp-content/uploads/2019/02/GettyImages-897118616.jpg?w=1024",
          "width": 1024,
          "height": 691,
          "title": null,
          "attribution": null,
          "isCached": true
        }
      ],
      "content": "\r\n",
      "type": "article",
      "ampWebUrl": "https://techcrunch.com/2021/03/19/uber-under-pressure-over-facial-recognition-checks-for-drivers/amp/",
      "cdnAmpWebUrl": "https://techcrunch-com.cdn.ampproject.org/c/s/techcrunch.com/2021/03/19/uber-under-pressure-over-facial-recognition-checks-for-drivers/amp/",
      "publishedDateTime": "2021-03-19T10:24:00-07:00",
      "updatedDateTime": null,
      "provider": {
        "name": "TechCrunch",
        "domain": "techcrunch.com",
        "images": [
          {
            "url": "https://smartableai.github.io/artificial-intelligence/assets/images/organizations/techcrunch.com-50x50.jpg",
            "width": 50,
            "height": 50,
            "title": null,
            "attribution": null,
            "isCached": false
          }
        ],
        "publishers": null,
        "authors": null
      },
      "locale": "en-us",
      "categories": [
        "news"
      ],
      "topics": [
        "Computer Vision",
        "AI"
      ]
    },
    {
      "path": "_news/2021-03-20-ai-designed-to-distinguish-croissants-from-crullers-and-other-pastries-proves-capable-of-identifying-cancerous-cells-on-microscope-slides-with.md",
      "title": "AI designed to distinguish croissants from crullers and other pastries proves capable of identifying cancerous cells on microscope slides with 99% accuracy",
      "excerpt": "The system uses deep learning for object recognition and instead of differentiating baked goods, the doctor hoped the technology could save lives. Identifying cancer cells to determine whether ...",
      "sourceUrl": null,
      "webUrl": "https://www.dailymail.co.uk/sciencetech/article-9381497/AI-designed-distinguish-types-pastries-identifies-cancer-99-accuracy.html",
      "originalUrl": "https://www.dailymail.co.uk/sciencetech/article-9381497/AI-designed-distinguish-types-pastries-identifies-cancer-99-accuracy.html",
      "featuredContent": null,
      "highlight": null,
      "heat": null,
      "tags": null,
      "images": [
        {
          "url": "https://i.dailymail.co.uk/1s/2021/03/19/17/40688578-0-image-a-23_1616173928996.jpg",
          "width": 636,
          "height": 382,
          "title": null,
          "attribution": null,
          "isCached": true
        }
      ],
      "content": "\r\n",
      "type": "article",
      "ampWebUrl": "https://www.dailymail.co.uk/sciencetech/article-9381497/amp/AI-designed-distinguish-types-pastries-identifies-cancer-99-accuracy.html",
      "cdnAmpWebUrl": "https://www-dailymail-co-uk.cdn.ampproject.org/c/s/www.dailymail.co.uk/sciencetech/article-9381497/amp/AI-designed-distinguish-types-pastries-identifies-cancer-99-accuracy.html",
      "publishedDateTime": "2021-03-19T10:15:00-07:00",
      "updatedDateTime": null,
      "provider": {
        "name": "Daily Mail",
        "domain": "dailymail.co.uk",
        "images": null,
        "publishers": null,
        "authors": null
      },
      "locale": "en-us",
      "categories": [
        "news"
      ],
      "topics": [
        "Computer Vision",
        "AI"
      ]
    },
    {
      "path": "_news/2021-03-20-solving-barren-plateaus-is-the-key-to-quantum-machine-learning.md",
      "title": "Solving 'barren plateaus' is the key to quantum machine learning",
      "excerpt": "Many machine learning algorithms on quantum computers suffer from the dreaded \"barren plateau\" of unsolvability, where they run into dead ends on optimization problems. This challenge had been relatively unstudied—until now.",
      "sourceUrl": null,
      "webUrl": "https://phys.org/news/2021-03-barren-plateaus-key-quantum-machine.html",
      "originalUrl": "https://phys.org/news/2021-03-barren-plateaus-key-quantum-machine.html",
      "featuredContent": null,
      "highlight": null,
      "heat": 89,
      "tags": null,
      "images": [
        {
          "url": "https://scx2.b-cdn.net/gfx/news/2021/solvingbarre.jpg",
          "width": 700,
          "height": 470,
          "title": null,
          "attribution": null,
          "isCached": true
        }
      ],
      "content": "\r\n",
      "type": "article",
      "ampWebUrl": "https://phys.org/news/2021-03-barren-plateaus-key-quantum-machine.amp",
      "cdnAmpWebUrl": "https://phys-org.cdn.ampproject.org/c/s/phys.org/news/2021-03-barren-plateaus-key-quantum-machine.amp",
      "publishedDateTime": "2021-03-19T10:01:00-07:00",
      "updatedDateTime": null,
      "provider": {
        "name": "Phys.org",
        "domain": "phys.org",
        "images": null,
        "publishers": null,
        "authors": null
      },
      "locale": "en-us",
      "categories": [
        "news"
      ],
      "topics": [
        "Machine Learning",
        "AI"
      ]
    },
    {
      "path": "_news/2021-03-19-facebook-messenger-bot-answers-questions-about-whats-recyclable.md",
      "title": "Facebook Messenger Bot Answers Questions About What’s Recyclable",
      "excerpt": "Facebook and leading consumer packaged goods brands like PepsiCo, organizers say. “We’ve built a lot of the answers into the bot experience so that it can be answered by artificial intelligence ...” says Cody Marshall, chief community strategy ...",
      "sourceUrl": null,
      "webUrl": "https://www.forbes.com/sites/jeffkart/2021/03/19/facebook-messenger-bot-answers-questions-about-whats-recyclable/",
      "originalUrl": "https://www.forbes.com/sites/jeffkart/2021/03/19/facebook-messenger-bot-answers-questions-about-whats-recyclable/",
      "featuredContent": null,
      "highlight": null,
      "heat": 114,
      "tags": null,
      "images": [
        {
          "url": "https://thumbor.forbes.com/thumbor/fit-in/1200x0/filters%3Aformat%28jpg%29/https%3A%2F%2Fspecials-images.forbesimg.com%2Fimageserve%2F6054caec32d36b83b9313d2b%2F0x0.jpg",
          "width": 1199,
          "height": 626,
          "title": null,
          "attribution": null,
          "isCached": true
        }
      ],
      "content": "\r\n",
      "type": "article",
      "ampWebUrl": "https://www.forbes.com/sites/jeffkart/2021/03/19/facebook-messenger-bot-answers-questions-about-whats-recyclable/amp/",
      "cdnAmpWebUrl": "https://www-forbes-com.cdn.ampproject.org/c/s/www.forbes.com/sites/jeffkart/2021/03/19/facebook-messenger-bot-answers-questions-about-whats-recyclable/amp/",
      "publishedDateTime": "2021-03-19T09:31:00-07:00",
      "updatedDateTime": null,
      "provider": {
        "name": "Forbes",
        "domain": "forbes.com",
        "images": [
          {
            "url": "https://smartableai.github.io/artificial-intelligence/assets/images/organizations/forbes.com-50x50.jpg",
            "width": 50,
            "height": 50,
            "title": null,
            "attribution": null,
            "isCached": false
          }
        ],
        "publishers": null,
        "authors": null
      },
      "locale": "en-us",
      "categories": [
        "news"
      ],
      "topics": [
        "Facebook AI",
        "AI"
      ]
    },
    {
      "path": "_news/2021-03-19-brian-brackeen-returns-as-an-advisor-to-facial-recognition-startup-kairos-following-his-ouster-as-ceo.md",
      "title": "Brian Brackeen returns as an advisor to facial recognition startup Kairos following his ouster as CEO",
      "excerpt": "Brian Brackeen, the founder and former CEO of facial recognition startup Kairos, has made his way back to the company following his ouster in 2018. Brackeen is now chairing the company’s scientific advisory board,",
      "sourceUrl": null,
      "webUrl": "https://techcrunch.com/2021/03/19/ousted-kairos-founder-returns-as-an-advisor-to-the-facial-recognition-startup/",
      "originalUrl": "https://techcrunch.com/2021/03/19/ousted-kairos-founder-returns-as-an-advisor-to-the-facial-recognition-startup/",
      "featuredContent": null,
      "highlight": null,
      "heat": 89,
      "tags": null,
      "images": [
        {
          "url": "https://techcrunch.com/wp-content/uploads/2018/09/43820546944_704c0ffc77_z.jpg?w=640",
          "width": 640,
          "height": 427,
          "title": null,
          "attribution": null,
          "isCached": true
        }
      ],
      "content": "\r\n",
      "type": "article",
      "ampWebUrl": "https://techcrunch.com/2021/03/19/ousted-kairos-founder-returns-as-an-advisor-to-the-facial-recognition-startup/amp/",
      "cdnAmpWebUrl": "https://techcrunch-com.cdn.ampproject.org/c/s/techcrunch.com/2021/03/19/ousted-kairos-founder-returns-as-an-advisor-to-the-facial-recognition-startup/amp/",
      "publishedDateTime": "2021-03-19T09:00:00-07:00",
      "updatedDateTime": null,
      "provider": {
        "name": "TechCrunch",
        "domain": "techcrunch.com",
        "images": [
          {
            "url": "https://smartableai.github.io/artificial-intelligence/assets/images/organizations/techcrunch.com-50x50.jpg",
            "width": 50,
            "height": 50,
            "title": null,
            "attribution": null,
            "isCached": false
          }
        ],
        "publishers": null,
        "authors": null
      },
      "locale": "en-us",
      "categories": [
        "news"
      ],
      "topics": [
        "Computer Vision",
        "AI"
      ]
    },
    {
      "path": "_news/2021-03-19-worldwide-artificial-intelligence-in-supply-chain-management-industry-to-2026-featuring-3m-adidas-and-amazon.md",
      "title": "Worldwide Artificial Intelligence in Supply Chain Management Industry to 2026 - Featuring 3M, Adidas and Amazon",
      "excerpt": "Disclaimer | Commerce Policy | Made In NYC | Stock quotes by finanzen.net DUBLIN, March 19, 2021 /PRNewswire/ -- The \"Artificial Intelligence ... Consumer Goods, Healthcare, Manufacturing, and ...",
      "sourceUrl": null,
      "webUrl": "https://markets.businessinsider.com/news/stocks/worldwide-artificial-intelligence-in-supply-chain-management-industry-to-2026-featuring-3m-adidas-and-amazon-1030228311",
      "originalUrl": "https://markets.businessinsider.com/news/stocks/worldwide-artificial-intelligence-in-supply-chain-management-industry-to-2026-featuring-3m-adidas-and-amazon-1030228311",
      "featuredContent": null,
      "highlight": null,
      "heat": null,
      "tags": null,
      "images": null,
      "content": "\r\n",
      "type": "article",
      "ampWebUrl": null,
      "cdnAmpWebUrl": null,
      "publishedDateTime": "2021-03-19T08:30:00-07:00",
      "updatedDateTime": null,
      "provider": {
        "name": "Business Insider",
        "domain": "businessinsider.com",
        "images": [
          {
            "url": "https://smartableai.github.io/artificial-intelligence/assets/images/organizations/businessinsider.com-50x50.jpg",
            "width": 50,
            "height": 50,
            "title": null,
            "attribution": null,
            "isCached": false
          }
        ],
        "publishers": null,
        "authors": null
      },
      "locale": "en-us",
      "categories": [
        "news"
      ],
      "topics": [
        "AI in Healthcare",
        "AI"
      ]
    },
    {
      "path": "_news/2021-03-19-automotive-artificial-intelligence-ai-market-size-development-key-opportunity-application-and-forecast-to-2026.md",
      "title": "Automotive Artificial Intelligence (AI) Market Size, Development, Key Opportunity, Application and Forecast to 2026",
      "excerpt": "The MarketWatch News Department was not involved in the creation of this content. Mar 19, 2021 (Market Insight Reports) -- Automotive Artificial Intelligence (AI) market report, inclusive of Covid-19 impact analysis, evaluates business status and potential ...",
      "sourceUrl": null,
      "webUrl": "https://www.marketwatch.com/press-release/automotive-artificial-intelligence-ai-market-size-development-key-opportunity-application-and-forecast-to-2026-2021-03-19",
      "originalUrl": "https://www.marketwatch.com/press-release/automotive-artificial-intelligence-ai-market-size-development-key-opportunity-application-and-forecast-to-2026-2021-03-19",
      "featuredContent": null,
      "highlight": null,
      "heat": 70,
      "tags": null,
      "images": [
        {
          "url": "https://mw3.wsj.net/mw5/content/logos/mw_logo_social.png",
          "width": 1200,
          "height": 630,
          "title": null,
          "attribution": null,
          "isCached": true
        }
      ],
      "content": "\r\n",
      "type": "article",
      "ampWebUrl": null,
      "cdnAmpWebUrl": null,
      "publishedDateTime": "2021-03-19T08:19:00-07:00",
      "updatedDateTime": null,
      "provider": {
        "name": "MarketWatch",
        "domain": "marketwatch.com",
        "images": [
          {
            "url": "https://smartableai.github.io/artificial-intelligence/assets/images/organizations/marketwatch.com-50x50.jpg",
            "width": 50,
            "height": 50,
            "title": null,
            "attribution": null,
            "isCached": false
          }
        ],
        "publishers": null,
        "authors": null
      },
      "locale": "en-us",
      "categories": [
        "news"
      ],
      "topics": [
        "AI"
      ]
    },
    {
      "path": "_news/2021-03-19-ibms-rob-thomas-details-key-ai-trends-in-shift-to-hybrid-cloud.md",
      "title": "IBM’s Rob Thomas details key AI trends in shift to hybrid cloud",
      "excerpt": "Join Transform 2021 for the most important themes in enterprise AI & Data. Learn more. The last year has seen a major spike in the adoption of AI models in production environments, in part driven ...",
      "sourceUrl": null,
      "webUrl": "https://venturebeat.com/2021/03/19/ibms-rob-thomas-details-key-ai-trends-in-shift-to-hybrid-cloud/",
      "originalUrl": "https://venturebeat.com/2021/03/19/ibms-rob-thomas-details-key-ai-trends-in-shift-to-hybrid-cloud/",
      "featuredContent": null,
      "highlight": null,
      "heat": 89,
      "tags": null,
      "images": [
        {
          "url": "https://venturebeat.com/wp-content/uploads/2021/03/IBM-e1616161696853.jpg?w=1200&strip=all",
          "width": 1200,
          "height": 600,
          "title": null,
          "attribution": null,
          "isCached": true
        }
      ],
      "content": "\r\n",
      "type": "article",
      "ampWebUrl": "https://venturebeat.com/2021/03/19/ibms-rob-thomas-details-key-ai-trends-in-shift-to-hybrid-cloud/amp/",
      "cdnAmpWebUrl": "https://venturebeat-com.cdn.ampproject.org/c/s/venturebeat.com/2021/03/19/ibms-rob-thomas-details-key-ai-trends-in-shift-to-hybrid-cloud/amp/",
      "publishedDateTime": "2021-03-19T07:32:00-07:00",
      "updatedDateTime": null,
      "provider": {
        "name": "VentureBeat",
        "domain": "venturebeat.com",
        "images": [
          {
            "url": "https://smartableai.github.io/artificial-intelligence/assets/images/organizations/venturebeat.com-50x50.jpg",
            "width": 50,
            "height": 50,
            "title": null,
            "attribution": null,
            "isCached": false
          }
        ],
        "publishers": null,
        "authors": null
      },
      "locale": "en-us",
      "categories": [
        "news"
      ],
      "topics": [
        "AI",
        "IBM AI"
      ]
    },
    {
      "path": "_news/2021-03-19-pangiam-acquires-veriscan-a-biometric-facial-recognition-system-for-airports-and-airlines.md",
      "title": "Pangiam Acquires veriScan, a Biometric Facial Recognition System for Airports and Airlines",
      "excerpt": "Pangiam, a technology-based security and travel services provider, announced today that it has acquired veriScan, an integrated biometric facial recognition system for airports and airlines, from the Metropolitan Washington Airports Authority (\"Airports Authority\").",
      "sourceUrl": null,
      "webUrl": "https://markets.businessinsider.com/news/stocks/pangiam-acquires-veriscan-a-biometric-facial-recognition-system-for-airports-and-airlines-1030228204",
      "originalUrl": "https://markets.businessinsider.com/news/stocks/pangiam-acquires-veriscan-a-biometric-facial-recognition-system-for-airports-and-airlines-1030228204",
      "featuredContent": null,
      "highlight": null,
      "heat": 104,
      "tags": null,
      "images": null,
      "content": "\r\n",
      "type": "article",
      "ampWebUrl": null,
      "cdnAmpWebUrl": null,
      "publishedDateTime": "2021-03-19T07:20:00-07:00",
      "updatedDateTime": null,
      "provider": {
        "name": "Business Insider",
        "domain": "businessinsider.com",
        "images": [
          {
            "url": "https://smartableai.github.io/artificial-intelligence/assets/images/organizations/businessinsider.com-50x50.jpg",
            "width": 50,
            "height": 50,
            "title": null,
            "attribution": null,
            "isCached": false
          }
        ],
        "publishers": null,
        "authors": null
      },
      "locale": "en-us",
      "categories": [
        "news"
      ],
      "topics": [
        "Computer Vision",
        "AI"
      ]
    },
    {
      "path": "_news/2021-03-19-resume-writing-tips-to-help-you-get-past-the-ai-gatekeepers.md",
      "title": "Résumé-Writing Tips to Help You Get Past the A.I. Gatekeepers",
      "excerpt": "More companies than ever are using software to screen their mountains of job applications. Getting seen by a human recruiter takes some effort.",
      "sourceUrl": null,
      "webUrl": "https://www.nytimes.com/2021/03/19/business/resume-filter-articial-intelligence.html",
      "originalUrl": "https://www.nytimes.com/2021/03/19/business/resume-filter-articial-intelligence.html",
      "featuredContent": null,
      "highlight": null,
      "heat": 172,
      "tags": null,
      "images": [
        {
          "url": "https://static01.nyt.com/images/2021/03/03/business/03Resumes-illo/03Resumes-illo-facebookJumbo.jpg",
          "width": 1050,
          "height": 550,
          "title": null,
          "attribution": null,
          "isCached": true
        }
      ],
      "content": "\r\n",
      "type": "article",
      "ampWebUrl": "https://www.nytimes.com/2021/03/19/business/resume-filter-articial-intelligence.amp.html",
      "cdnAmpWebUrl": "https://www-nytimes-com.cdn.ampproject.org/c/s/www.nytimes.com/2021/03/19/business/resume-filter-articial-intelligence.amp.html",
      "publishedDateTime": "2021-03-19T07:00:00-07:00",
      "updatedDateTime": null,
      "provider": {
        "name": "New York Times",
        "domain": "nytimes.com",
        "images": [
          {
            "url": "https://smartableai.github.io/artificial-intelligence/assets/images/organizations/nytimes.com-50x50.jpg",
            "width": 50,
            "height": 50,
            "title": null,
            "attribution": null,
            "isCached": false
          }
        ],
        "publishers": null,
        "authors": null
      },
      "locale": "en-us",
      "categories": [
        "news"
      ],
      "topics": [
        "AI",
        "AI in Autos"
      ]
    },
    {
      "path": "_news/2021-03-19-replica-studios-makes-it-easy-for-game-and-filmmakers-to-create-ai-character-voices.md",
      "title": "Replica Studios makes it easy for game and filmmakers to create AI character voices",
      "excerpt": "AI voice technology startup Replica Studios has launched a desktop app that makes it easier for game and filmmakers to create voices.",
      "sourceUrl": null,
      "webUrl": "https://venturebeat.com/2021/03/19/replica-studios-makes-it-easy-for-game-and-filmmakers-to-create-ai-character-voices/",
      "originalUrl": "https://venturebeat.com/2021/03/19/replica-studios-makes-it-easy-for-game-and-filmmakers-to-create-ai-character-voices/",
      "featuredContent": null,
      "highlight": null,
      "heat": 81,
      "tags": null,
      "images": [
        {
          "url": "https://venturebeat.com/wp-content/uploads/2021/03/replica.jpg?w=1200&strip=all",
          "width": 1200,
          "height": 625,
          "title": null,
          "attribution": null,
          "isCached": true
        }
      ],
      "content": "\r\n",
      "type": "article",
      "ampWebUrl": "https://venturebeat.com/2021/03/19/replica-studios-makes-it-easy-for-game-and-filmmakers-to-create-ai-character-voices/amp/",
      "cdnAmpWebUrl": "https://venturebeat-com.cdn.ampproject.org/c/s/venturebeat.com/2021/03/19/replica-studios-makes-it-easy-for-game-and-filmmakers-to-create-ai-character-voices/amp/",
      "publishedDateTime": "2021-03-19T06:00:00-07:00",
      "updatedDateTime": null,
      "provider": {
        "name": "VentureBeat",
        "domain": "venturebeat.com",
        "images": [
          {
            "url": "https://smartableai.github.io/artificial-intelligence/assets/images/organizations/venturebeat.com-50x50.jpg",
            "width": 50,
            "height": 50,
            "title": null,
            "attribution": null,
            "isCached": false
          }
        ],
        "publishers": null,
        "authors": null
      },
      "locale": "en-us",
      "categories": [
        "news"
      ],
      "topics": [
        "AI"
      ]
    },
    {
      "path": "_news/2021-03-19-artificial-intelligence-in-digital-pathology-upcoming-webinar-hosted-by-xtalks.md",
      "title": "Artificial Intelligence in Digital Pathology, Upcoming Webinar Hosted by Xtalks",
      "excerpt": "Which artificial intelligence method will work best with your image data? Image analysis is an essential part of digital",
      "sourceUrl": null,
      "webUrl": "https://www.benzinga.com/pressreleases/21/03/n20252581/artificial-intelligence-in-digital-pathology-upcoming-webinar-hosted-by-xtalks",
      "originalUrl": "https://www.benzinga.com/pressreleases/21/03/n20252581/artificial-intelligence-in-digital-pathology-upcoming-webinar-hosted-by-xtalks",
      "featuredContent": null,
      "highlight": null,
      "heat": null,
      "tags": null,
      "images": null,
      "content": "\r\n",
      "type": "article",
      "ampWebUrl": "https://amp.benzinga.com/amp/content/20252581",
      "cdnAmpWebUrl": "https://amp-benzinga-com.cdn.ampproject.org/c/s/amp.benzinga.com/amp/content/20252581",
      "publishedDateTime": "2021-03-19T05:30:00-07:00",
      "updatedDateTime": null,
      "provider": {
        "name": "Benzinga.com",
        "domain": "benzinga.com",
        "images": null,
        "publishers": null,
        "authors": null
      },
      "locale": "en-us",
      "categories": [
        "news"
      ],
      "topics": [
        "AI in Healthcare",
        "AI"
      ]
    },
    {
      "path": "_news/2021-03-19-forget-tesla-this-1-tsx-stock-is-a-better-driverless-auto-play.md",
      "title": "Forget Tesla! This 1 TSX Stock Is a Better Driverless Auto Play",
      "excerpt": "The future is of automotive is more than just clean and green; it's also driverless. And Tesla isn’t the only promising company in this arena.",
      "sourceUrl": null,
      "webUrl": "https://www.fool.ca/2021/03/19/forget-tesla-this-1-tsx-stock-is-a-better-driverless-auto-play/",
      "originalUrl": "https://www.fool.ca/2021/03/19/forget-tesla-this-1-tsx-stock-is-a-better-driverless-auto-play/",
      "featuredContent": null,
      "highlight": null,
      "heat": 104,
      "tags": null,
      "images": [
        {
          "url": "https://yw553ftvhw1iqegz29fycoyw-wpengine.netdna-ssl.com/wp-content/uploads/2019/03/Self-Driving-Cars.jpg",
          "width": 1000,
          "height": 563,
          "title": null,
          "attribution": null,
          "isCached": true
        }
      ],
      "content": "\r\n",
      "type": "article",
      "ampWebUrl": "https://www.fool.ca/2021/03/19/forget-tesla-this-1-tsx-stock-is-a-better-driverless-auto-play/amp/",
      "cdnAmpWebUrl": "https://www-fool-ca.cdn.ampproject.org/c/s/www.fool.ca/2021/03/19/forget-tesla-this-1-tsx-stock-is-a-better-driverless-auto-play/amp/",
      "publishedDateTime": "2021-03-19T05:08:00-07:00",
      "updatedDateTime": null,
      "provider": {
        "name": "The Motley Fool Canada",
        "domain": "fool.ca",
        "images": null,
        "publishers": null,
        "authors": null
      },
      "locale": "en-us",
      "categories": [
        "news"
      ],
      "topics": [
        "AI in Autos",
        "AI"
      ]
    },
    {
      "path": "_news/2021-03-19-lays-uses-ai-to-create-messi-messages-bringing-the-soccer-superstar-to-your-phone.md",
      "title": "Lay's uses AI to create Messi Messages, bringing the soccer superstar to your phone",
      "excerpt": "Now you can get specialized messages from soccer legend Lionel Messi, thanks to a fun Lay's program. Anyone who has ever dreamed of getting a video message from legendary Argentine soccer star Lionel Messi is in luck.",
      "sourceUrl": null,
      "webUrl": "https://www.techrepublic.com/article/lays-uses-ai-to-create-messi-messages-bringing-the-soccer-superstar-to-your-phone/",
      "originalUrl": "https://www.techrepublic.com/article/lays-uses-ai-to-create-messi-messages-bringing-the-soccer-superstar-to-your-phone/",
      "featuredContent": null,
      "highlight": null,
      "heat": 83,
      "tags": null,
      "images": [
        {
          "url": "https://www.techrepublic.com/a/hub/i/r/2021/03/19/8b52349d-e26f-42e9-94ff-9158dfafcc38/resize/1200x/ef1795f4de0a8e819b8e6ebc03f0a8cd/img-58683874.png",
          "width": 1200,
          "height": 604,
          "title": null,
          "attribution": null,
          "isCached": true
        }
      ],
      "content": "\r\n",
      "type": "article",
      "ampWebUrl": "https://www.techrepublic.com/google-amp/article/lays-uses-ai-to-create-messi-messages-bringing-the-soccer-superstar-to-your-phone/",
      "cdnAmpWebUrl": "https://www-techrepublic-com.cdn.ampproject.org/c/s/www.techrepublic.com/google-amp/article/lays-uses-ai-to-create-messi-messages-bringing-the-soccer-superstar-to-your-phone/",
      "publishedDateTime": "2021-03-19T05:02:00-07:00",
      "updatedDateTime": null,
      "provider": {
        "name": "TechRepublic",
        "domain": "techrepublic.com",
        "images": [
          {
            "url": "https://smartableai.github.io/artificial-intelligence/assets/images/organizations/techrepublic.com-50x50.jpg",
            "width": 50,
            "height": 50,
            "title": null,
            "attribution": null,
            "isCached": false
          }
        ],
        "publishers": null,
        "authors": null
      },
      "locale": "en-us",
      "categories": [
        "news"
      ],
      "topics": [
        "AI Hardware",
        "AI"
      ]
    },
    {
      "path": "_news/2021-03-19-pangiam-bets-on-facial-recognition-to-speed-travelers-through-airports-post-covid.md",
      "title": "Pangiam Bets on Facial Recognition to Speed Travelers Through Airports Post-Covid",
      "excerpt": "Travel tech firm Pangiam is betting this is only the beginning with the acquisition of the facial recognition system VeriScan from the Washington, D.C., airports operator. Imagine passing through ...",
      "sourceUrl": null,
      "webUrl": "https://skift.com/2021/03/19/pangiam-bets-on-facial-recognition-to-speed-travelers-through-airports-post-covid/",
      "originalUrl": "https://skift.com/2021/03/19/pangiam-bets-on-facial-recognition-to-speed-travelers-through-airports-post-covid/",
      "featuredContent": null,
      "highlight": null,
      "heat": 99,
      "tags": null,
      "images": [
        {
          "url": "https://skift.com/wp-content/uploads/2021/03/IMG_0310.jpg",
          "width": 1024,
          "height": 683,
          "title": null,
          "attribution": null,
          "isCached": true
        }
      ],
      "content": "\r\n",
      "type": "article",
      "ampWebUrl": "https://skift.com/2021/03/19/pangiam-bets-on-facial-recognition-to-speed-travelers-through-airports-post-covid/amp/",
      "cdnAmpWebUrl": "https://skift-com.cdn.ampproject.org/c/s/skift.com/2021/03/19/pangiam-bets-on-facial-recognition-to-speed-travelers-through-airports-post-covid/amp/",
      "publishedDateTime": "2021-03-19T05:00:00-07:00",
      "updatedDateTime": null,
      "provider": {
        "name": "Skift",
        "domain": "skift.com",
        "images": null,
        "publishers": null,
        "authors": null
      },
      "locale": "en-us",
      "categories": [
        "news"
      ],
      "topics": [
        "Computer Vision",
        "AI"
      ]
    },
    {
      "path": "_news/2021-03-19-13-startups-selected-to-join-microsoft-ai-for-social-impact-programme.md",
      "title": "13 startups selected to join Microsoft AI for Social Impact programme",
      "excerpt": "Microsoft has announced that it will work with 13 startups to develop artificial intelligence solutions under its AI for Social Impact scheme",
      "sourceUrl": null,
      "webUrl": "https://www.information-age.com/13-startups-selected-to-join-microsoft-ai-for-social-impact-programme-123494361/",
      "originalUrl": "https://www.information-age.com/13-startups-selected-to-join-microsoft-ai-for-social-impact-programme-123494361/",
      "featuredContent": null,
      "highlight": null,
      "heat": 84,
      "tags": null,
      "images": [
        {
          "url": "https://s27389.pcdn.co/wp-content/uploads/2021/03/13-startups-selected-to-join-microsoft-ai-for-social-impact-programme.jpeg",
          "width": 1013,
          "height": 675,
          "title": null,
          "attribution": null,
          "isCached": true
        }
      ],
      "content": "\r\n",
      "type": "article",
      "ampWebUrl": null,
      "cdnAmpWebUrl": null,
      "publishedDateTime": "2021-03-19T04:21:00-07:00",
      "updatedDateTime": null,
      "provider": {
        "name": "Information Age",
        "domain": "information-age.com",
        "images": null,
        "publishers": null,
        "authors": null
      },
      "locale": "en-us",
      "categories": [
        "news"
      ],
      "topics": [
        "Microsoft AI",
        "AI"
      ]
    },
    {
      "path": "_news/2021-03-19-niti-aayog-aws-partner-to-train-students-on-cloud-computing.md",
      "title": "Niti Aayog, AWS partner to train students on cloud computing",
      "excerpt": "IT major Amazon Web Services (AWS) and Niti Aayog has announced a tie-up to train students on the fundamentals of cloud computing through Atal Tinkering Labs. A statement of intent (SoI) was signed between Niti Aayog and Amazon Internet Services Private Limited (AISPL),",
      "sourceUrl": null,
      "webUrl": "https://www.sakshieducation.com/StoryA.aspx?cid=0&sid=0&chid=0&tid=0&nid=289383",
      "originalUrl": "https://www.sakshieducation.com/StoryA.aspx?cid=0&sid=0&chid=0&tid=0&nid=289383",
      "featuredContent": null,
      "highlight": null,
      "heat": null,
      "tags": null,
      "images": [
        {
          "url": "https://www.sakshieducation.com/images/logo.png",
          "width": 510,
          "height": 300,
          "title": null,
          "attribution": null,
          "isCached": true
        }
      ],
      "content": "\r\n",
      "type": "article",
      "ampWebUrl": null,
      "cdnAmpWebUrl": null,
      "publishedDateTime": "2021-03-19T03:42:00-07:00",
      "updatedDateTime": null,
      "provider": {
        "name": "Sakshi Education",
        "domain": "sakshieducation.com",
        "images": null,
        "publishers": null,
        "authors": null
      },
      "locale": "en-us",
      "categories": [
        "news"
      ],
      "topics": [
        "AWS AI",
        "AI"
      ]
    },
    {
      "path": "_news/2021-03-19-ibms-project-debater-showcases-next-gen-ai-driven-productivity.md",
      "title": "IBM’s Project Debater showcases next-gen AI-driven productivity",
      "excerpt": "I’ve been following IBM’s Watson effort since the beginning — and its initial focus on winning the game Jeopardy. This early effort was just a taste of what this platform could do. Years later, I attended the introduction of Project Debater,",
      "sourceUrl": null,
      "webUrl": "https://www.computerworld.com/article/3612349/ibm-s-project-debater-showcases-next-gen-ai-driven-productivity.html",
      "originalUrl": "https://www.computerworld.com/article/3612349/ibm-s-project-debater-showcases-next-gen-ai-driven-productivity.html",
      "featuredContent": null,
      "highlight": null,
      "heat": 79,
      "tags": null,
      "images": [
        {
          "url": "https://images.idgesg.net/images/article/2018/08/brain_mind_circuits_connections_artificial_intelligence_by_metamorworks_gettyimages-949321092_1200x800-100767997-large.jpg",
          "width": 1200,
          "height": 800,
          "title": null,
          "attribution": null,
          "isCached": true
        }
      ],
      "content": "\r\n",
      "type": "article",
      "ampWebUrl": "https://www.computerworld.com/article/3612349/ibm-s-project-debater-showcases-next-gen-ai-driven-productivity.amp.html",
      "cdnAmpWebUrl": "https://www-computerworld-com.cdn.ampproject.org/c/s/www.computerworld.com/article/3612349/ibm-s-project-debater-showcases-next-gen-ai-driven-productivity.amp.html",
      "publishedDateTime": "2021-03-19T02:42:00-07:00",
      "updatedDateTime": null,
      "provider": {
        "name": "Computerworld",
        "domain": "computerworld.com",
        "images": null,
        "publishers": null,
        "authors": null
      },
      "locale": "en-us",
      "categories": [
        "news"
      ],
      "topics": [
        "IBM AI",
        "AI"
      ]
    },
    {
      "path": "_news/2021-03-19-job-trend-analysis-marks-growth-of-data-science-ai-roles.md",
      "title": "Job trend analysis marks growth of data science, AI roles",
      "excerpt": "The demand for these sought-after positions continues to grow in importance, according to analysis of job openings for March 2021 conducted by LHH.",
      "sourceUrl": null,
      "webUrl": "https://www.techrepublic.com/article/job-trend-analysis-marks-growth-of-data-science-ai-roles/",
      "originalUrl": "https://www.techrepublic.com/article/job-trend-analysis-marks-growth-of-data-science-ai-roles/",
      "featuredContent": null,
      "highlight": null,
      "heat": 117,
      "tags": null,
      "images": [
        {
          "url": "https://www.techrepublic.com/a/hub/i/r/2020/11/11/44436744-fe4e-4eaf-bdbe-c943f9889f46/resize/1200x/ec4c1fe64d24827800bfe87676c10f69/metamorworks-11.jpg",
          "width": 1200,
          "height": 900,
          "title": null,
          "attribution": null,
          "isCached": true
        }
      ],
      "content": "\r\n",
      "type": "article",
      "ampWebUrl": "https://www.techrepublic.com/google-amp/article/job-trend-analysis-marks-growth-of-data-science-ai-roles/",
      "cdnAmpWebUrl": "https://www-techrepublic-com.cdn.ampproject.org/c/s/www.techrepublic.com/google-amp/article/job-trend-analysis-marks-growth-of-data-science-ai-roles/",
      "publishedDateTime": "2021-03-19T02:39:00-07:00",
      "updatedDateTime": null,
      "provider": {
        "name": "TechRepublic",
        "domain": "techrepublic.com",
        "images": [
          {
            "url": "https://smartableai.github.io/artificial-intelligence/assets/images/organizations/techrepublic.com-50x50.jpg",
            "width": 50,
            "height": 50,
            "title": null,
            "attribution": null,
            "isCached": false
          }
        ],
        "publishers": null,
        "authors": null
      },
      "locale": "en-us",
      "categories": [
        "news"
      ],
      "topics": [
        "AI"
      ]
    },
    {
      "path": "_news/2021-03-19-40-women-leading-the-way-in-ai-innovation.md",
      "title": "40 women leading the way in AI innovation",
      "excerpt": "IBM's annual list of Women Leaders in artificial intelligence includes women from 18 countries who serve in a variety of roles.",
      "sourceUrl": null,
      "webUrl": "https://www.techrepublic.com/article/40-women-leading-the-way-in-ai-innovation/",
      "originalUrl": "https://www.techrepublic.com/article/40-women-leading-the-way-in-ai-innovation/",
      "featuredContent": null,
      "highlight": null,
      "heat": 127,
      "tags": null,
      "images": [
        {
          "url": "https://www.techrepublic.com/a/hub/i/r/2019/06/05/a80a4f1a-e4aa-467a-b85e-0802f7169f61/resize/1200x/83b223eeaad78cde0d4502b429298252/women.jpg",
          "width": 1200,
          "height": 900,
          "title": null,
          "attribution": null,
          "isCached": true
        }
      ],
      "content": "\r\n",
      "type": "article",
      "ampWebUrl": "https://www.techrepublic.com/google-amp/article/40-women-leading-the-way-in-ai-innovation/",
      "cdnAmpWebUrl": "https://www-techrepublic-com.cdn.ampproject.org/c/s/www.techrepublic.com/google-amp/article/40-women-leading-the-way-in-ai-innovation/",
      "publishedDateTime": "2021-03-19T02:12:00-07:00",
      "updatedDateTime": null,
      "provider": {
        "name": "TechRepublic",
        "domain": "techrepublic.com",
        "images": [
          {
            "url": "https://smartableai.github.io/artificial-intelligence/assets/images/organizations/techrepublic.com-50x50.jpg",
            "width": 50,
            "height": 50,
            "title": null,
            "attribution": null,
            "isCached": false
          }
        ],
        "publishers": null,
        "authors": null
      },
      "locale": "en-us",
      "categories": [
        "news"
      ],
      "topics": [
        "AI",
        "IBM AI"
      ]
    },
    {
      "path": "_news/2021-03-19-artificial-consciousness-how-to-give-a-robot-a-soul.md",
      "title": "Artificial Consciousness: How To Give A Robot A Soul",
      "excerpt": "But when artificial intelligence first started, no one could have predicted the things it can do today. Sure, people imagined robot helpers à la the Jetsons or advanced transportation à la Epcot ...",
      "sourceUrl": null,
      "webUrl": "https://futurism.com/artificial-consciousness",
      "originalUrl": "https://futurism.com/artificial-consciousness",
      "featuredContent": null,
      "highlight": null,
      "heat": null,
      "tags": null,
      "images": [
        {
          "url": "https://wp-assets.futurism.com/2018/06/conscious-600x315.png",
          "width": 600,
          "height": 315,
          "title": null,
          "attribution": null,
          "isCached": true
        }
      ],
      "content": "\r\n",
      "type": "article",
      "ampWebUrl": "https://futurism.com/artificial-consciousness/amp",
      "cdnAmpWebUrl": "https://futurism-com.cdn.ampproject.org/c/s/futurism.com/artificial-consciousness/amp",
      "publishedDateTime": "2021-03-19T01:48:00-07:00",
      "updatedDateTime": null,
      "provider": {
        "name": "Futurism",
        "domain": "futurism.com",
        "images": null,
        "publishers": null,
        "authors": null
      },
      "locale": "en-us",
      "categories": [
        "news"
      ],
      "topics": [
        "AI in Robotics",
        "AI"
      ]
    }
  ],
  "nextPage": 24
}